libdir/__init__.py
libdir/helloworld.py
metastasiz/__init__.py
metastasiz/helloworld.py
metastasiz/path.py
metastasiz/utils.py
module1/__init__.py
module1/helloworld.py
metastasiz-0.1.1.dist-info/METADATA
metastasiz-0.1.1.dist-info/WHEEL
metastasiz-0.1.1.dist-info/top_level.txt
metastasiz-0.1.1.dist-info/RECORD
